README.md
setup.py
scCAMUS/__init__.py
scCAMUS/metric.py
scCAMUS/preprocess.py
scCAMUS.egg-info/PKG-INFO
scCAMUS.egg-info/SOURCES.txt
scCAMUS.egg-info/dependency_links.txt
scCAMUS.egg-info/not-zip-safe
scCAMUS.egg-info/requires.txt
scCAMUS.egg-info/top_level.txt