Metadata-Version: 2.1
Name: scCAMUS
Version: 1.0.1
Summary: Cross-datasets annotation modeling with universal reference data and method selection
Home-page: https://github.com/Zhanglabtools/CAMUS
Author: Qunlun Shen
Author-email: knotnet@foxmail.com
License: MIT
Requires-Dist: requests
